ChatChess/ChatChess.py
ChatChess/__init__.py
chatchess-1.1.9.dist-info/LICENSE
chatchess-1.1.9.dist-info/METADATA
chatchess-1.1.9.dist-info/WHEEL
chatchess-1.1.9.dist-info/top_level.txt
chatchess-1.1.9.dist-info/RECORD
