Metadata-Version: 2.1
Name: chatchess
Version: 1.1.9
Summary: A package to play chess with ChatGPT
Home-page: https://github.com/Tmate6/ChatChess
Author: Mate Tohai
Author-email: admin@tmate6.com
Classifier: Programming Language :: Python :: 3
Classifier: License :: OSI Approved :: GNU General Public License v3 (GPLv3)
Classifier: Operating System :: OS Independent
License-File: LICENSE
Requires-Dist: chess
Requires-Dist: openai
